decoder.v
// Decoder circuit
`define NOT not #50
`define AND and #50
`define OR or #50
`define NAND nand #50
`define NOR nor #50
`define XOR xor #50

module behavioralDecoder
(
    output out0, out1, out2, out3,
    input address0, address1,
    input enable
);
    // Uses concatenation and shift operators
    assign {out3,out2,out1,out0}=enable<<{address1,address0};
endmodule


module structuralDecoder
(
    output out0, out1, out2, out3,
    input address0, address1,
    input enable
);
// out0 = n0andn1
// out1 = only 0
// out2 = only 1
// out3 = 0and1

  wire a0enable;
  wire a1enable;
  wire na0enable;
  wire na1enable;
  wire na0andna1;

  `AND andgate0enable(a0enable, address0, enable);
  `AND andgate1enable(a1enable, address1, enable);

  `NOT address0inv(na0enable, a0enable);
  `NOT address1inv(na1enable, a1enable);

  `AND andgate0and1(out3, a0enable, a1enable);
  `AND andgaten0andn1(na0andna1, na0enable, na1enable);
  `AND andgate0andn1(out1, a0enable, na1enable);
  `AND andgaten0and1(out2, na0enable, a1enable);
  `AND andgaten0n1enable(out0, enable, na0andna1);

    // Your decoder code here
endmodule

decoder.t.v
// Decoder testbench
`timescale 1 ns / 1 ps
`include "decoder.v"

module testDecoder ();
    reg addr0, addr1;
    reg enable;
    wire out0,out1,out2,out3;

    //behavioralDecoder decoder (out0,out1,out2,out3,addr0,addr1,enable);
    structuralDecoder decoder (out0,out1,out2,out3,addr0,addr1,enable); // Swap after testing

    initial begin
    $display("En A0 A1| O0 O1 O2 O3 | Expected Output");
    enable=0;addr0=0;addr1=0; #1000
    $display("%b  %b  %b |  %b  %b  %b  %b | All false", enable, addr0, addr1, out0, out1, out2, out3);
    enable=0;addr0=1;addr1=0; #1000
    $display("%b  %b  %b |  %b  %b  %b  %b | All false", enable, addr0, addr1, out0, out1, out2, out3);
    enable=0;addr0=0;addr1=1; #1000
    $display("%b  %b  %b |  %b  %b  %b  %b | All false", enable, addr0, addr1, out0, out1, out2, out3);
    enable=0;addr0=1;addr1=1; #1000
    $display("%b  %b  %b |  %b  %b  %b  %b | All false", enable, addr0, addr1, out0, out1, out2, out3);
    enable=1;addr0=0;addr1=0; #1000
    $display("%b  %b  %b |  %b  %b  %b  %b | O0 Only", enable, addr0, addr1, out0, out1, out2, out3);
    enable=1;addr0=1;addr1=0; #1000
    $display("%b  %b  %b |  %b  %b  %b  %b | O1 Only", enable, addr0, addr1, out0, out1, out2, out3);
    enable=1;addr0=0;addr1=1; #1000
    $display("%b  %b  %b |  %b  %b  %b  %b | O2 Only", enable, addr0, addr1, out0, out1, out2, out3);
    enable=1;addr0=1;addr1=1; #1000
    $display("%b  %b  %b |  %b  %b  %b  %b | O3 Only", enable, addr0, addr1, out0, out1, out2, out3);
    $finish();
    end

    initial begin
    enable=0;addr0=0;addr1=0; #1000
    $dumpfile("decoder.vcd");
    $dumpvars(0, testDecoder);
    end

endmodule

decoder.vcd
$date
	Wed Sep 19 15:16:54 2018
$end
$version
	Icarus Verilog
$end
$timescale
	1ps
$end
$scope module testDecoder $end
$var wire 1 ! out0 $end
$var wire 1 " out1 $end
$var wire 1 # out2 $end
$var wire 1 $ out3 $end
$var reg 1 % addr0 $end
$var reg 1 & addr1 $end
$var reg 1 ' enable $end
$scope module decoder $end
$var wire 1 ( a0enable $end
$var wire 1 ) a1enable $end
$var wire 1 * address0 $end
$var wire 1 + address1 $end
$var wire 1 , enable $end
$var wire 1 - na0andna1 $end
$var wire 1 . na0enable $end
$var wire 1 / na1enable $end
$var wire 1 ! out0 $end
$var wire 1 " out1 $end
$var wire 1 # out2 $end
$var wire 1 $ out3 $end
$upscope $end
$upscope $end
$enddefinitions $end
#1000000
$dumpvars
1/
1.
1-
0,
0+
1*
0)
0(
0'
0&
1%
0$
0#
0"
0!
$end
#2000000
1&
1+
0%
0*
#3000000
1%
1*
#4000000
0&
0+
0%
0*
1'
1,
#4050000
1!
#5000000
1%
1*
#5050000
1(
#5100000
0.
1"
#5150000
0-
#5200000
0!
#6000000
1&
1+
0%
0*
#6050000
1)
0(
#6100000
0/
1.
0"
#6150000
1#
#7000000
1%
1*
#7050000
1(
#7100000
0.
1$
#7150000
0#
