adder.v
// Adder circuita
`define NOT not #50
`define AND and #50
`define OR or #50
`define NAND nand #50
`define NOR nor #50
`define XOR xor #50

module behavioralFullAdder
(
    output sum,
    output carryout,
    input a,
    input b,
    input carryin
);
    // Uses concatenation operator and built-in '+'
    assign {carryout, sum}=a+b+carryin;
endmodule

module structuralFullAdder
(
    output sum,
    output carryout,
    input a,
    input b,
    input carryin
);

    wire AandB, AandCin, BandCin, AxorB;

    `AND andgateAB(AandB, a, b);
    `AND andgateACin(AandCin, a, carryin);
    `AND andgateBCin(BandCin, b, carryin);
    `OR orgateAllAnds(carryout, AandB, AandCin, BandCin);
    `XOR xorAB(AxorB, a, b);
    `XOR xorAll(sum, AxorB, carryin);
    // Your adder code here
endmodule

adder.t.v
// Adder testbench
`timescale 1 ns / 1 ps
`include "adder.v"

module testFullAdder();
    reg a, b, carryin;
    wire sum, carryout;

    //behavioralFullAdder adder (sum, carryout, a, b, carryin);
    structuralFullAdder adder (sum, carryout, a, b, carryin);

    initial begin
    $display("a b carryin | sum carryout | Expected: Sum Carryout");
    a=0;b=0;carryin=0; #1000
    $display("%b %b %b       | %b  %b         |            0   0", a, b, carryin, sum, carryout);
    a=0;b=1;carryin=0; #1000
    $display("%b %b %b       | %b  %b         |            1   0", a, b, carryin, sum, carryout);
    a=1;b=0;carryin=0; #1000
    $display("%b %b %b       | %b  %b         |            1   0", a, b, carryin, sum, carryout);
    a=1;b=1;carryin=0; #1000
    $display("%b %b %b       | %b  %b         |            0   1", a, b, carryin, sum, carryout);
    a=0;b=0;carryin=1; #1000
    $display("%b %b %b       | %b  %b         |            1   0", a, b, carryin, sum, carryout);
    a=0;b=1;carryin=1; #1000
    $display("%b %b %b       | %b  %b         |            0   1", a, b, carryin, sum, carryout);
    a=1;b=0;carryin=1; #1000
    $display("%b %b %b       | %b  %b         |            0   1", a, b, carryin, sum, carryout);
    a=1;b=1;carryin=1; #1000
    $display("%b %b %b       | %b  %b         |            1   1", a, b, carryin, sum, carryout);
    end

    initial begin
    a=0;b=0;carryin=0; #1000
    $dumpfile("fullAdder.vcd");
    $dumpvars(0, testFullAdder);
    end
  endmodule

fullAdder.vcd
$date
	Wed Sep 19 15:25:34 2018
$end
$version
	Icarus Verilog
$end
$timescale
	1ps
$end
$scope module testFullAdder $end
$var wire 1 ! carryout $end
$var wire 1 " sum $end
$var reg 1 # a $end
$var reg 1 $ b $end
$var reg 1 % carryin $end
$scope module adder $end
$var wire 1 & AandB $end
$var wire 1 ' AandCin $end
$var wire 1 ( AxorB $end
$var wire 1 ) BandCin $end
$var wire 1 * a $end
$var wire 1 + b $end
$var wire 1 , carryin $end
$var wire 1 ! carryout $end
$var wire 1 " sum $end
$upscope $end
$upscope $end
$enddefinitions $end
#1000000
$dumpvars
0,
1+
0*
0)
0(
0'
0&
0%
1$
0#
0"
0!
$end
#1050000
1(
#1100000
1"
#2000000
0$
0+
1#
1*
#3000000
1$
1+
#3050000
1&
0(
#3100000
1!
0"
#4000000
1%
1,
0$
0+
0#
0*
#4050000
1"
0&
#4100000
0!
#5000000
1$
1+
#5050000
1)
1(
#5100000
1!
0"
#6000000
0$
0+
1#
1*
#6050000
0)
1'
#7000000
1$
1+
#7050000
1&
1)
0(
#7100000
1"
