multiplexer.v
// Multiplexer circuit
`define NOT not #50
`define AND and #50
`define OR or #50
`define NAND nand #50
`define NOR nor #50
`define XOR xor #50

module behavioralMultiplexer
(
    output out,
    input address0, address1,
    input in0, in1, in2, in3
);
    // Join single-bit inputs into a bus, use address as index
    wire[3:0] inputs = {in3, in2, in1, in0};
    wire[1:0] address = {address1, address0};
    assign out = inputs[address];
endmodule


module structuralMultiplexer
(
    output out,
    input address0, address1,
    input in0, in1, in2, in3
);

  wire a0anda1, a0xora1, a0only, a1only;
  wire in0select, in1select, in2select;
  wire n0, n1, n0andn1, in3select;

  `AND andgate0and1(a0anda1, address0, address1);
  `AND andgatein3(in3select, in3, a0anda1);
  `XOR xorselect(a0xora1, address0, address1);
  `AND andgatea0(a0only, address0, a0xora1);
  `AND andgatea1(a1only, address1, a0xora1);
  `AND andgatein1(in1select, in1, a0only);
  `AND andgatein2(in2select, in2, a1only);
  `NOT not0(n0, address0);
  `NOT not1(n1, address1);
  `AND andgaten0andn1(n0andn1, n0, n1);
  `AND andgatein0(in0select, n0andn1, in0);
  `OR orselects(out, in0select, in1select, in2select, in3select);


endmodule

multiplexer.t.v
// Multiplexer testbench
`timescale 1 ns / 1 ps
`include "multiplexer.v"

module testMultiplexer ();
  // Your test code here
  reg in0, in1, in2, in3;
  reg address0, address1;
  wire out;

  //behavioralMultiplexer multiplexer (out,address0,address1,in0,in1,in2,in3);
  structuralMultiplexer multiplexer (out,address0,address1,in0,in1,in2,in3);

  initial begin
  $display("in0 in1 in2 in3| a0 a1| out | Expected Output");
  in0=0;in1=0;in2=0;in3=0;address0=0;address1=0; #1000
  $display("%b   %b   %b   %b  | %b  %b |  %b  | 0", in0, in1, in2, in3, address0, address1, out);
  in0=1;in1=0;in2=0;in3=0;address0=0;address1=0; #1000
  $display("%b   %b   %b   %b  | %b  %b |  %b  | 1", in0, in1, in2, in3, address0, address1, out);
  in0=0;in1=0;in2=0;in3=0;address0=1;address1=0; #1000
  $display("%b   %b   %b   %b  | %b  %b |  %b  | 0", in0, in1, in2, in3, address0, address1, out);
  in0=0;in1=1;in2=0;in3=0;address0=1;address1=0; #1000
  $display("%b   %b   %b   %b  | %b  %b |  %b  | 1", in0, in1, in2, in3, address0, address1, out);
  in0=0;in1=0;in2=0;in3=0;address0=0;address1=1; #1000
  $display("%b   %b   %b   %b  | %b  %b |  %b  | 0", in0, in1, in2, in3, address0, address1, out);
  in0=0;in1=0;in2=1;in3=0;address0=0;address1=1; #1000
  $display("%b   %b   %b   %b  | %b  %b |  %b  | 1", in0, in1, in2, in3, address0, address1, out);
  in0=0;in1=0;in2=0;in3=0;address0=1;address1=1; #1000
  $display("%b   %b   %b   %b  | %b  %b |  %b  | 0", in0, in1, in2, in3, address0, address1, out);
  in0=0;in1=0;in2=0;in3=1;address0=1;address1=1; #1000
  $display("%b   %b   %b   %b  | %b  %b |  %b  | 1", in0, in1, in2, in3, address0, address1, out);
  end

  initial begin
  in0=0;in1=0;in2=0;in3=0;address0=0;address1=0; #1000
  $dumpfile("multiplexer.vcd");
  $dumpvars(0, testMultiplexer);
  end

endmodule

multiplexer.vcd
$date
	Wed Sep 19 15:21:08 2018
$end
$version
	Icarus Verilog
$end
$timescale
	1ps
$end
$scope module testMultiplexer $end
$var wire 1 ! out $end
$var reg 1 " address0 $end
$var reg 1 # address1 $end
$var reg 1 $ in0 $end
$var reg 1 % in1 $end
$var reg 1 & in2 $end
$var reg 1 ' in3 $end
$scope module multiplexer $end
$var wire 1 ( a0anda1 $end
$var wire 1 ) a0only $end
$var wire 1 * a0xora1 $end
$var wire 1 + a1only $end
$var wire 1 , address0 $end
$var wire 1 - address1 $end
$var wire 1 . in0 $end
$var wire 1 / in0select $end
$var wire 1 0 in1 $end
$var wire 1 1 in1select $end
$var wire 1 2 in2 $end
$var wire 1 3 in2select $end
$var wire 1 4 in3 $end
$var wire 1 5 in3select $end
$var wire 1 6 n0 $end
$var wire 1 7 n0andn1 $end
$var wire 1 8 n1 $end
$var wire 1 ! out $end
$upscope $end
$upscope $end
$enddefinitions $end
#1000000
$dumpvars
18
17
16
05
04
03
02
01
00
0/
1.
0-
0,
0+
0*
0)
0(
0'
0&
0%
1$
0#
0"
0!
$end
#1050000
1/
#1100000
1!
#2000000
1"
1,
0$
0.
#2050000
1*
06
0/
#2100000
1)
07
0!
#3000000
1%
10
#3050000
11
#3100000
1!
#4000000
1#
1-
0"
0,
0%
00
#4050000
1+
08
0)
16
01
#4100000
0!
#5000000
1&
12
#5050000
13
#5100000
1!
#6000000
1"
1,
0&
02
#6050000
1(
0*
1)
06
03
#6100000
0)
0+
0!
#7000000
1'
14
#7050000
15
#7100000
1!
